souJpg/__init__.py
souJpg/comm/__init__.py
souJpg/comm/apiResponse.py
souJpg/comm/contextManagers.py
souJpg/comm/cos.py
souJpg/comm/dbHelper.py
souJpg/comm/dbsCL.py
souJpg/comm/hdfsUtils.py
souJpg/comm/imageUtils.py
souJpg/comm/kafkaOps.py
souJpg/comm/labelUtils.py
souJpg/comm/mathUtils.py
souJpg/comm/projectUitls.py
souJpg/comm/redisOps.py
souJpg/comm/sparkApp.py
souJpg/comm/sparkBase.py
souJpg/comm/test.py
souJpg/comm/threadPools.py
souJpg/comm/utils.py
souJpg/comm/vcgUtils.py
souJpg/comm/videoUtils.py
souJpg/comm/cfg/__init__.py
souJpg/comm/cfg/utils.py
souJpg/comm/cfg/vcgCfg.py
souJpg/comm/decorators/__init__.py
souJpg/comm/decorators/base.py
souJpg/comm/decorators/comm.py
souJpg/comm/decorators/methodRetry.py
souJpg/comm/es/__init__.py
souJpg/comm/es/es.py
souJpg/comm/es/test/__init__.py
souJpg/comm/es/test/test.py
souJpg/comm/fs/__init__.py
souJpg/comm/fs/comm.py
souJpg/comm/fs/distributeFs.py
souJpg/comm/ops/__init__.py
souJpg/comm/ops/ops.py
souJpg/comm/ops/test/__init__.py
souJpg/comm/ops/test/test.py
souJpg/comm/test/__init__.py
souJpg/comm/test/test.py
souJpg_comm_opensearch_dev-1.0.8.dist-info/METADATA
souJpg_comm_opensearch_dev-1.0.8.dist-info/WHEEL
souJpg_comm_opensearch_dev-1.0.8.dist-info/top_level.txt
souJpg_comm_opensearch_dev-1.0.8.dist-info/RECORD
