Metadata-Version: 2.1
Name: souJpg-comm-opensearch-dev
Version: 1.0.8
Summary: elasticsearch to opensearch
Home-page: 
Author: zhaoyufei
Author-email: 
Classifier: Programming Language :: Python :: 3
Classifier: License :: OSI Approved :: MIT License
Classifier: Operating System :: OS Independent
Requires-Python: >=3.8.10
Requires-Dist: mysql-connector-python
Requires-Dist: requests
Requires-Dist: pandas
Requires-Dist: pymongo
Requires-Dist: PyYAML
Requires-Dist: selectivesearch
Requires-Dist: pyarrow
Requires-Dist: opencv-contrib-python (==4.5.5.64)
Requires-Dist: opencv-python-headless (==4.5.5.64)
Requires-Dist: opencv-python (==4.7.0.68)
Requires-Dist: imgaug (==0.4.0)
Requires-Dist: loguru
Requires-Dist: opensearch-py
Requires-Dist: fastapi
Requires-Dist: uvicorn
Requires-Dist: shortuuid
Requires-Dist: streamlit (==1.13.0)
Requires-Dist: locust
Requires-Dist: redis
Requires-Dist: redisbloom
Requires-Dist: strsimpy
Requires-Dist: cos-python-sdk-v5
Requires-Dist: minio
Requires-Dist: tqdm
Requires-Dist: kafka-python
Requires-Dist: spacy
Requires-Dist: streamlit-drawable-canvas (==0.9.0)
Requires-Dist: streamlit-cropper (==0.2.0)
Requires-Dist: tencentcloud-sdk-python
Requires-Dist: tencentcloud-sdk-python-sts
Requires-Dist: qcloud-python-sts
Requires-Dist: scikit-learn
Requires-Dist: apscheduler
Requires-Dist: nltk
Requires-Dist: omegaconf
Requires-Dist: twine
